vshieldpy/__init__.py
vshieldpy/auth.py
vshieldpy/client.py
vshieldpy/api_defs/__init__.py
vshieldpy/api_defs/auto_renew.py
vshieldpy/api_defs/graphs.py
vshieldpy/api_defs/invoices.py
vshieldpy/api_defs/locations.py
vshieldpy/api_defs/operating_systems.py
vshieldpy/api_defs/paths.py
vshieldpy/api_defs/payment.py
vshieldpy/api_defs/plans.py
vshieldpy/api_defs/request.py
vshieldpy/api_defs/status_codes.py
vshieldpy/api_defs/stocks.py
vshieldpy/api_defs/tasks.py
vshieldpy/api_defs/transactions.py
vshieldpy/api_defs/type_defs.py
vshieldpy/api_defs/uam_status.py
vshieldpy/exceptions/auth_exceptions.py
vshieldpy/exceptions/base_exception.py
vshieldpy/exceptions/id_exceptions.py
vshieldpy/exceptions/parameter_exceptions.py
vshieldpy/handlers/__init__.py
vshieldpy/handlers/billing.py
vshieldpy/handlers/firewall.py
vshieldpy/handlers/servers.py
vshieldpy/handlers/services.py
vshieldpy/handlers/system.py
vshieldpy/helpers/__init__.py
vshieldpy/products/__init__.py
vshieldpy/products/firewall.py
vshieldpy/products/server.py
vshieldpy/products/service.py
vshieldpy-0.0.2.dist-info/METADATA
vshieldpy-0.0.2.dist-info/WHEEL
vshieldpy-0.0.2.dist-info/licenses/LICENSE
vshieldpy-0.0.2.dist-info/RECORD
