Metadata-Version: 2.3
Name: vshieldpy
Version: 0.0.2
Summary: Python library for interacting with the vShield API.
Project-URL: Homepage, https://github.com/airblast-dev/vshieldpy
Project-URL: Issues, https://github.com/airblast-dev/vshieldpy/issues
Project-URL: Docs, https://vshieldpy.readthedocs.io/en/latest/
Author-email: Tayfun Bocek <tayfunbocek@live.ca>
License-File: LICENSE
Keywords: servers,virtaul server,vps,vshield,web
Classifier: Environment :: Web Environment
Classifier: Intended Audience :: Developers
Classifier: License :: OSI Approved :: MIT License
Classifier: Operating System :: OS Independent
Classifier: Programming Language :: Python :: 3 :: Only
Classifier: Programming Language :: Python :: 3.10
Classifier: Programming Language :: Python :: 3.11
Classifier: Programming Language :: Python :: 3.12
Requires-Python: >=3.10
Requires-Dist: httpx[http2]>=0.27.0
Provides-Extra: dev
Requires-Dist: anyio[trio]>=4.3.0; extra == 'dev'
Requires-Dist: flask>=3.0.2; extra == 'dev'
Requires-Dist: pytest-env>=1.1.3; extra == 'dev'
Requires-Dist: ruff; extra == 'dev'
Provides-Extra: docs
Requires-Dist: enum-tools>=0.11.0; extra == 'docs'
Requires-Dist: sphinx-rtd-theme>=2.0.0; extra == 'docs'
Requires-Dist: sphinx-toolbox>=3.5.0; extra == 'docs'
Requires-Dist: sphinx>=3.4.0; extra == 'docs'
Provides-Extra: testing
Requires-Dist: anyio[trio]>=4.3.0; extra == 'testing'
Requires-Dist: flask>=3.0.2; extra == 'testing'
Requires-Dist: pytest-env>=1.1.3; extra == 'testing'
